<?xml version="1.0" encoding="utf-8"?>
<XnaContent>
  <Asset Type="RenderingSystem.RendererImpl.ParticleSettings">
    <BlendState>NonPremultiplied</BlendState>
    <TextureName>particles/smoke</TextureName>
    <MaxParticles>200</MaxParticles>
    <Duration>PT3S</Duration>
    <DurationRandomness>1.5</DurationRandomness>
    <EmissionRate>5</EmissionRate>
    <EmitterVelocitySensitivity>0.1</EmitterVelocitySensitivity>
    <MinHorizontalVelocity>0</MinHorizontalVelocity>
    <MaxHorizontalVelocity>0.1</MaxHorizontalVelocity>
    <MinVerticalVelocity>-0.1</MinVerticalVelocity>
    <MaxVerticalVelocity>0.1</MaxVerticalVelocity>
    <Gravity>0 0 0</Gravity>
    <EndVelocity>1</EndVelocity>
    <MinColor>FF406080</MinColor>
    <MaxColor>80FFFFFF</MaxColor>
    <MinRotateSpeed>-4</MinRotateSpeed>
    <MaxRotateSpeed>4</MaxRotateSpeed>
    <MinStartSize>0.2</MinStartSize>
    <MaxStartSize>0.4</MaxStartSize>
    <MinEndSize>0.5</MinEndSize>
    <MaxEndSize>1.5</MaxEndSize>
  </Asset>
</XnaContent>